{
  "$id": "http://example.com/example.json",
  "type": "object",
  "definitions": {},
  "$schema": "http://json-schema.org/draft-07/schema#",
  "properties": {
    "code": {
      "$id": "/properties/code",
      "type": "string",
      "title": "The Code Schema ",
      "default": "",
      "examples": [
        "000000"
      ]
    },
    "message": {
      "$id": "/properties/message",
      "type": "string",
      "title": "The Message Schema ",
      "default": "",
      "examples": [
        "成功"
      ]
    },
    "showInfoPage": {
      "$id": "/properties/showInfoPage",
      "type": "object",
      "properties": {
        "itemCounts": {
          "$id": "/properties/showInfoPage/properties/itemCounts",
          "type": "integer",
          "title": "The Itemcounts Schema ",
          "default": 0,
          "examples": [
            56
          ]
        },
        "currentPage": {
          "$id": "/properties/showInfoPage/properties/currentPage",
          "type": "integer",
          "title": "The Currentpage Schema ",
          "default": 0,
          "examples": [
            1
          ]
        },
        "pageSize": {
          "$id": "/properties/showInfoPage/properties/pageSize",
          "type": "integer",
          "title": "The Pagesize Schema ",
          "default": 0,
          "examples": [
            10
          ]
        },
        "pageCounts": {
          "$id": "/properties/showInfoPage/properties/pageCounts",
          "type": "integer",
          "title": "The Pagecounts Schema ",
          "default": 0,
          "examples": [
            6
          ]
        },
        "targets": {
          "$id": "/properties/showInfoPage/properties/targets",
          "type": "array",
          "items": {
            "$id": "/properties/showInfoPage/properties/targets/items",
            "type": "object",
            "properties": {
              "position": {
                "$id": "/properties/showInfoPage/properties/targets/items/properties/position",
                "type": "string",
                "title": "The Position Schema ",
                "default": "",
                "examples": [
                  "03"
                ]
              },
              "thumbUrl": {
                "$id": "/properties/showInfoPage/properties/targets/items/properties/thumbUrl",
                "type": "string",
                "title": "The Thumburl Schema ",
                "default": "",
                "examples": [
                  "http://uat-steam.opg.cn/_static/admin/images/resource/20180604111435_222285.png"
                ]
              },
              "bannerUrl": {
                "$id": "/properties/showInfoPage/properties/targets/items/properties/bannerUrl",
                "type": "string",
                "title": "The Bannerurl Schema ",
                "default": "",
                "examples": [
                  "http://uat-steam.opg.cn/_static/admin/images/resource/20180604111435_222285.png"
                ]
              },
              "resourceId": {
                "$id": "/properties/showInfoPage/properties/targets/items/properties/resourceId",
                "type": "integer",
                "title": "The Resourceid Schema ",
                "default": 0,
                "examples": [
                  2011
                ]
              },
              "title": {
                "$id": "/properties/showInfoPage/properties/targets/items/properties/title",
                "type": "string",
                "title": "The Title Schema ",
                "default": "",
                "examples": [
                  "STEAM教育：提升孩子哪些能力？"
                ]
              },
              "subHead": {
                "$id": "/properties/showInfoPage/properties/targets/items/properties/subHead",
                "type": "null",
                "title": "The Subhead Schema ",
                "default": null,
                "examples": [
                  null
                ]
              },
              "activityAddress": {
                "$id": "/properties/showInfoPage/properties/targets/items/properties/activityAddress",
                "onlyof":{
                              "type": "null",
                              "type": "null"
                            },
                "title": "The Activityaddress Schema ",
                "default": null,
                "examples": [
                  null
                ]
              },
              "holdingTime": {
                "$id": "/properties/showInfoPage/properties/targets/items/properties/holdingTime",
                "type": "integer",
                "title": "The Holdingtime Schema ",
                "default": 0,
                "examples": [
                  0
                ]
              },
              "originalPrice": {
                "$id": "/properties/showInfoPage/properties/targets/items/properties/originalPrice",
                "anyof":{
                           "type": "null",
                           "type": "string"
                          },
                "title": "The Originalprice Schema ",
                "default": null,
                "examples": [
                  null
                ]
              },
              "minPrice": {
                "$id": "/properties/showInfoPage/properties/targets/items/properties/minPrice",
                "anyof":{
                              "type": "number",
                              "type":null
                          },
                "title": "The Minprice Schema ",
                "default": null,
                "examples": [
                  null
                ]
              },
              "state": {
                "$id": "/properties/showInfoPage/properties/targets/items/properties/state",
                "type": "boolean",
                "title": "The State Schema ",
                "default": false,
                "examples": [
                  true
                ]
              },
              "specificType": {
                "$id": "/properties/showInfoPage/properties/targets/items/properties/specificType",
                "type": "string",
                "title": "The Specifictype Schema ",
                "default": "",
                "examples": [
                  "素质教育"
                ]
              },
              "resourceType": {
                "$id": "/properties/showInfoPage/properties/targets/items/properties/resourceType",
                "type": "integer",
                "title": "The Resourcetype Schema ",
                "default": 0,
                "examples": [
                  2
                ]
              },
              "collects": {
                "$id": "/properties/showInfoPage/properties/targets/items/properties/collects",
                "type": "integer",
                "title": "The Collects Schema ",
                "default": 0,
                "examples": [
                  31
                ]
              },
              "visits": {
                "$id": "/properties/showInfoPage/properties/targets/items/properties/visits",
                "type": "integer",
                "title": "The Visits Schema ",
                "default": 0,
                "examples": [
                  66757
                ]
              },
              "sales": {
                "$id": "/properties/showInfoPage/properties/targets/items/properties/sales",
                "type": "integer",
                "title": "The Sales Schema ",
                "default": 0,
                "examples": [
                  0
                ]
              },
              "collectState": {
                "$id": "/properties/showInfoPage/properties/targets/items/properties/collectState",
                "type": "integer",
                "title": "The Collectstate Schema ",
                "default": 0,
                "examples": [
                  2
                ]
              }
            }
          }
        }
      }
    }
  }
}